{
    "2026-04-24": {
        "rows": [
            "quality_3",
            "quality_2",
            "quality_1"
        ],
        "cols": [
            "itempool_angel",
            "itempool_devil",
            "itempool_treasure"
        ],
        "items": [
            [],
            [],
            [],
            [],
            [],
            [],
            [],
            [],
            []
        ]
    },
    "2026-04-25": {
        "rows": [
            "itempool_treasure",
            "itempool_devil",
            "itempool_angel"
        ],
        "cols": [
            "quality_3",
            "quality_4",
            "quality_2"
        ],
        "items": [
            [],
            [],
            [],
            [],
            [],
            [],
            [],
            [],
            []
        ]
    }
}